{
  "id": "service",
  "type": "SharedSlice",
  "name": "Service",
  "description": "Service",
  "variations": [
    {
      "id": "default",
      "name": "Default",
      "docURL": "...",
      "version": "initial",
      "description": "Default",
      "imageUrl": "",
      "primary": {
        "service_title": {
          "type": "Text",
          "config": {
            "label": "Service Title",
            "placeholder": ""
          }
        },
        "service_headline": {
          "type": "Text",
          "config": {
            "label": "Service Headline",
            "placeholder": ""
          }
        },
        "service_image": {
          "type": "Image",
          "config": {
            "label": "Service Image",
            "constraint": {},
            "thumbnails": []
          }
        },
        "service_link": {
          "type": "Link",
          "config": {
            "label": "Service Link",
            "placeholder": "",
            "select": null,
            "allowTargetBlank": true,
            "allowText": true,
            "repeat": false
          }
        }
      },
      "items": {}
    },
    {
      "id": "homeService",
      "name": "homeService",
      "docURL": "...",
      "version": "initial",
      "description": "Default",
      "imageUrl": "",
      "primary": {
        "title": {
          "type": "Text",
          "config": {
            "label": "Title",
            "placeholder": ""
          }
        },
        "service_data": {
          "type": "Group",
          "config": {
            "label": "Service Data",
            "repeat": true,
            "fields": {
              "service_title": {
                "type": "Text",
                "config": {
                  "label": "Service Title",
                  "placeholder": ""
                }
              },
              "service_description": {
                "type": "Text",
                "config": {
                  "label": "Service Description",
                  "placeholder": ""
                }
              },
              "service_image": {
                "type": "Image",
                "config": {
                  "label": "Service Image",
                  "constraint": {},
                  "thumbnails": []
                }
              },
              "service_headline": {
                "type": "Text",
                "config": {
                  "label": "Service Headline",
                  "placeholder": ""
                }
              },
              "service_link": {
                "type": "Link",
                "config": {
                  "label": "Service Link",
                  "placeholder": "",
                  "select": null,
                  "allowTargetBlank": true,
                  "allowText": true,
                  "repeat": false
                }
              }
            }
          }
        }
      },
      "items": {}
    }
  ]
}